{"title":"Pregledač Orijentisanih snimaka","currentFootprint":"Postojeći otisak","accuracy":"Tačnost","accuracyInformation":"Tačnost se izračunava pomoću svojstva Tačnost orijentacije definisanog u servisu sloja orijentisanih snimaka.","additionalFootprints":"Dodatni otisci","additionalCameraLocations":"Dodatne lokacije kamere","groundArea":"Oblast tla","groundDistance":"Razdaljina do tla","imageAttributes":"Atributi snimka","imageEnhancement":"Poboljšanje snimka","imageGallery":"Galerija snimaka","float":"Plutaj","dock":"Dock","footprint":"Otisak","heightAboveGround":"Visina iznad zemlje","groundLocation":"Lokacija tla","noImageError":"Nema dostupnih snimaka za odabranu lokaciju.","onLoadMessage":"Izaberite lokaciju na mapi da vidite prikaz.","imageLoadError":"Došlo je do greške prilikom učitavanja slike.","measurementTools":"Alatke za merenje snimaka","measurementTable":"Tabela merenja","mapImageConversionTool":"Alatka za lociranje slike mape","brightness":"Osvetljenje","contrast":"Kontrast","sharpness":"Oštrina","navigationTool":"Alat za navigaciju","noLocalPort":"Vrednost za lokalni port nije obezbeđena. Lokalni port je potreban za učitavanje lokalnih snimaka.","noAttachment":"Nijedan snimak i prilog nisu dostupni za odabranu lokaciju.","currentFootprintTooltip":"Uključi/isključi vidljivost prikazanih otisaka slika.","additionalFootprintsTooltip":"Uključi/isključi vidljivost ili dodatne otiske koji sadrže lokaciju koja je u pitanju.","additionalCameraLocationsTooltip":"Uključi/isključi vidljivost svih dodatnih lokacija kamera i slika koje sadrže lokaciju koja je u pitanju.","navigationTooltip":"Istražite povratne slike u vezi sa lokacijom koja je u pitanju.","imageEnhancementTooltip":"Podesite svetlost, kontrast i oštrinu slike.","imageGalleryTooltip":"Istražite sličice svih slika koje prikazuju lokaciju od interesa.","mapImageConversionTooltip":"Kliknite na sliku da vidite gde se ta lokacija nalazi na mapi i obrnuto.","newMeasurement":"Novo merenje","unsupportedPanoramicImageryError":"Pregledač trenutno ne podržava vizuelizaciju slika od {datasetFormat} 360 stepeni.","showPopups":"Prikaži iskačuće prozore","startMeasurement":"Započni merenje","overlayCameraLocations":"Preklapajuće lokacije kamere","overlayMapFeatures":"Preklapajući geoobjekti mape","imageOverlays":"Preklapanje snimaka","invalidCameraHeadingWarningTitle":"Nevažeći CameraHeading","invalidCameraHeadingWarningDescription":"Vrednost CameraHeading je nevažeća za izabrani snimak. Svi alati za pregled orijentisanih snimaka koji koriste CameraHeading vrednost su onemogućeni. Dodelite važeću vrednost za ovo polje u tabeli atributa kako biste omogućili alate.","createFeaturesFromImage":"Kreirajte geoobjekte iz snimka","value":"Vrednost"}