{"title":"Oriented Imagery Viewer","currentFootprint":"ฟุตปรินท์ปัจจุบัน","accuracy":"ความถูกต้อง","accuracyInformation":"ความแม่นยำจะถูกคำนวณโดยใช้คุณสมบัติความแม่นยำทิศทางภาพที่กำหนดค่าไว้ในบริการของชั้นข้อมูล Oriented Imagery","additionalFootprints":"ฟุตปรินท์เพิ่มเติม","additionalCameraLocations":"ตำแหน่งกล้องเพิ่มเติม","groundArea":"พื้นดิน","groundDistance":"ระยะห่างบนดิน","imageAttributes":"แอตทริบิวต์รูปภาพ","imageEnhancement":"ปรับแต่งรูปภาพ","imageGallery":"แกลเลอรีรูปภาพ","float":"ลอย","dock":"ด็อค","footprint":"ฟุตปรินท์","heightAboveGround":"ความสูงเหนือพื้นดิน","groundLocation":"ตำแหน่งบนดิน","noImageError":"ไม่มีรูปภาพที่พร้อมใช้งานสำหรับตำแหน่งที่ตั้งที่เลือก","onLoadMessage":"เลือกตำแหน่งบนแผนที่เพื่อดูภาพ","imageLoadError":"เกิดข้อผิดพลาดขณะโหลดภาพ","measurementTools":"เครื่องมือการวัดภาพ","measurementTable":"ตารางการวัด","mapImageConversionTool":"เครื่องมือตำแหน่งภาพแผนที่","brightness":"ความสว่าง","contrast":"ความแตกต่างของสว่างมืด","sharpness":"ความคมชัด","navigationTool":"เครื่องมือการนำทาง","noLocalPort":"ไม่ได้ระบุค่าสำหรับพอร์ตโลคัล ไม่จำเป็นต้องใช้พอร์ตโลคัลในการโหลดภาพโลคัล","noAttachment":"ไม่มีรูปภาพหรือไฟล์แนบที่พร้อมใช้งานสำหรับตำแหน่งที่ตั้งที่เลือก","currentFootprintTooltip":"สลับการแสดงฟุตปรินท์ของภาพที่แสดงผล","additionalFootprintsTooltip":"สลับการแสดงฟุตปรินท์เพิ่มเติมทั้งหมดที่มีตำแหน่งที่สนใจ","additionalCameraLocationsTooltip":"สลับการแสดงตำแหน่งกล้องเพิ่มเติมทั้งหมดของภาพที่มีตำแหน่งที่สนใจ","navigationTooltip":"สำรวจภาพที่ถูกส่งคืนตามความสัมพันธ์กับตำแหน่งที่สนใจ","imageEnhancementTooltip":"ปรับความสว่าง คอนทราสต์ และเพิ่มความคมชัดของภาพ","imageGalleryTooltip":"สำรวจรูปขนาดย่อของภาพทั้งหมดซึ่งแสดงตำแหน่งที่สนใจ","mapImageConversionTooltip":"คลิกที่แต่ละภาพเพื่อดูว่าตำแหน่งนั้นอยู่ที่ใดบนแผนที่ และทำสลับกัน","newMeasurement":"การวัดใหม่","unsupportedPanoramicImageryError":"ขณะนี้ Viewer ไม่รองรับการแสดงผล {datasetFormat} ภาพแบบ 360 องศา","showPopups":"แสดงป็อปอัพ","startMeasurement":"เริ่มการวัด","overlayCameraLocations":"การซ้อนทับตำแหน่งกล้อง","overlayMapFeatures":"การซ้อนทับฟีเจอร์แผนที่","imageOverlays":"โอเวอร์เลย์ภาพ","invalidCameraHeadingWarningTitle":"CameraHeading ใช้งานไม่ได้","invalidCameraHeadingWarningDescription":"ค่า CameraHeading ใช้งานไม่ได้สำหรับภาพที่เลือก เครื่องมือ oriented imagery viewer ทั้งหมดที่ใช้ค่า CameraHeading ถูกปิดใช้งานไว้ กำหนดค่าที่ใช้งานได้สำหรับฟิลด์ในตารางคุณลักษณะ เพื่อเปิดใช้งานเครื่องมือ","createFeaturesFromImage":"สร้างฟีเจอร์จากภาพ","value":"ค่า"}