{"widgetLabel":"Forma prvku","empty":"Bez hodnoty","showAll":"Zobraziť všetko","showAllOptions":"Zobraziť všetky možnosti","recommended":"Odporúčané","all":"Všetky","recommendedOptions":"Odporúčané možnosti","allOptions":"Všetky možnosti","valueExpressionError":"Nepodarilo sa vypočítať hodnotu","validationErrors":{"cannotBeNull":"Prosím zadajte hodnotu","outsideRange":"Hodnota by mala byť medzi {min} a {max}","outsideRangeMax":"Hodnota by mala byť nižšia alebo rovná {max}","outsideRangeMin":"Hodnota by mala byť väčšia alebo rovná {min}","invalidCodedValue":"Hodnota by mala byť jednou z hodnôt na zozname.","invalidType":"Nie je platná hodnota","tooShort":"Toto pole požaduje minimálne {min} znakov","valuesIncompatible":"Hodnota je nekompatibilná s inými vybranými hodnotami","valuesDoNotMatch":"Hodnota sa nezhoduje s inými vybranými hodnotami"},"viewAll":"Zobraziť všetko","totalCount":"Celkový počet: {count}","addRecord":"Pridať záznam","addFeature":"Pridať prvok","editRecord":"Editovať záznam","editFeature":"Editovať prvok","requiredFieldLabel":"{name} - povinné pole","relatedRecordsList":"Súvisiace záznamy","associations":{"associatedLayers":"Asociované vrstvy","associatedFeatures":"Asociované prvky","associationSettings":"Nastavenia asociácie","availableLayers":"Dostupné vrstvy","availableFeatures":"Dostupné prvky","midspanEdge":"Stred hrany","endpointEdge":"Koncový bod hrany","edgeSide":"Strana hrany","toSide":"Do","fromSide":"Od","attachment":"Príloha","connectivity":"Pripojenie","container":"Kontajner","content":"Obsah","structure":"Štruktúra","terminal":"Terminál","terminalComboboxLabel":"Vyberte terminál","edgeConnectionComboboxLabel":"Vyberte pripojenie hrany","visible":"Viditeľné","connectTo":"Pripojiť k","midspanLocation":"Stredové umiestnenie","rulesToggle":"Zobraziť len prvky so sieťovými pravidlami","filterOptions":"Filtrovať možnosti","filterLayers":"Filtrovať vrstvy","filterFeatures":"Filtrovať prvky"},"noOriginKeyFeature":"Prvok nemôže byť pridaný do '{relatedLayerName}' pokiaľ '{originKeyField}' nebol zadaný.","noOriginKeyRecord":"Záznam nemôže byť pridaný do'{relatedLayerName}' pokiaľ '{originKeyField}' nebol zadaný.","subtypes":{"changeWarning":"Subtyp {newType} môže mať iné predvolené hodnoty ako {originalType}. Zachovanie aktuálnych hodnôt môže spôsobiť neočakávané výsledky.","changeWarningTitle":"Subtyp sa zmenil","useDefaultValuesOption":"Použiť predvolené hodnoty","keepCurrentValuesOption":"Ponechať aktuálne hodnoty","unsupportedDomainGroupTitle":"Nepodporované","fieldOutOfSubtypeDomainWarning":"Hodnota tohto poľa je mimo rozsahu domény."}}