{"widgetLabel":"Geoobjekttabell","header":"{title} (Totalt: {count} | Utvalg: {selected})","headerNoSelection":"{title} (Totalt: {count})","untitled":"Uten tittel","relatedRecords":"Relaterte poster","attachments":"Vedlegg","loading":"Laster inn...","syncing":"Synkroniserer...","errorData":"Datafeil.","errorLayer":"Lagfeil.","errorUpdateFailed":"Oppdateringen mislyktes.","errorDomainType":"Domenetypen støttes ikke.","show":"Vis","hide":"Skjul","menu":"Meny","options":"Alternativer","allColums":"Alle kolonner","sortAsc":"Sorter stigende","sortDesc":"Sorter synkende","toggleColumns":"Vis/skjul kolonner","clearSelection":"Tøm utvalg","centerOnSelection":"Sentrer på utvalg","showSelected":"Vis utvalg","filter":"Filter","addField":"Legg til felt","refreshData":"Oppdater data","date":"Dato","number":"Tall","string":"Streng","showAllRecords":"Vis alle","zoomToSelection":"Zoom til utvalg","deleteSelection":"Slett utvalg","deleteSelectionCount":"Slett utvalg: {count}","deleteRecordsRemoved":"Postene fjernes for godt.","keepRecords":"Behold poster","recordsCount":"Poster ({count})","noLayer":"Ikke noe lag","exitRelatedRecords":"Avslutt relaterte poster","showAllTables":"Vis alle tabeller","selectALayer":"Velg et lag","exportSelectionCSV":"Eksporter utvalg til CSV","noValue":"Ingen verdi","editingPreventedColumn":"Redigering er forhindret for celler i denne kolonnen.","subtypes":{"changeWarning":"Undertypen {newType} kan ha forskjellige standardverier enn {originalType}. Hvis du beholder de nåværende verdiene, kan det føre til uventede resultater.","changeWarningTitle":"Undertype endret","useDefaultValuesOption":"Bruk standardverdier","keepCurrentValuesOption":"Behold gjeldende verdier","unsupportedDomainGroupTitle":"Ikke støttet","fieldOutOfSubtypeDomainWarning":"Feltets verdi er utenfor området for dets domene."},"addAttachment":"Legg til vedlegg","attachmentsCount":"Vedlegg ({count})","attachmentThumbnail":"Miniatyrbilde for vedlegg","deleteAttachment":"Slett vedlegg","deleteAttachmentConfirmation":"Er du sikker på at du vil slette vedleggene?","deleteAttachmentCount":"Slett vedlegg ({count})","downloadAttachment":"Last ned vedlegg","dragAndDropToUpload":"Dra og slipp filen for å laste opp et vedlegg.","editingDisabled":"Redigering er deaktivert","editingRestricted":"Redigering er begrenset","errorFileName":"Opplastingen mislyktes. Filnavnet er for langt.","errorFileSize":"Opplastingen mislyktes. Filen er for stor","errorFileUnsupported":"Opplastingen mislyktes. Filtypen støttes ikke","errorOccured":"Det oppstod en feil","exitAttachments":"Gå ut av vedleggsvisning","fileName":"Filnavn","noAttachments":"Det er ingen vedlegg","noFeature":"Ingen geoobjekt oppgitt","replaceFile":"Erstatt fil","selectedCount":"Valgte: {count}","selectFile":"Velg fil","size":"Størrelse","updateAttachment":"Oppdater vedlegg","viewAttachment":"Vis vedlegg","viewAttachments":"Vis vedlegg"}