{"widgetLabel":"Ominaisuus","fields":"Kentät","fieldsSummary":"Ominaisuustietojen ja arvojen luettelo","media":"Media","next":"Seuraava","noTitle":"Nimetön","previous":"Edellinen","lastEdited":"Muokattu viimeksi: {date}.","lastCreated":"Luontipäivä: {date}.","lastEditedByUser":"{user} on muokannut viimeksi {date}.","lastCreatedByUser":"{user} on luonut {date}.","loadingError":"Tämän kohteen tietoja ei voi näyttää.","showAll":"Näytä kaikki","numberRecords":"Yhteensä: {number}","relatedFeaturesList":"Liittyvät tietueet","noRelatedFeatures":"Tietueita ei löytynyt.","relationshipNotFound":"Suhdetta ei löydy kartasta.","pageText":"{index}/{total}","associationsAttachments":"Rakenteiset liitteet","associationsConnectivity":"Yhdistyvyys","associationsContainer":"Säilö","associationsContents":"Sisältö","associationsJunctionEdgeFrom":"Risteys–reuna kohteesta","associationsJunctionEdgeMidspan":"Risteys–reunan keskiväli","associationsJunctionEdgeTo":"Risteys–reuna kohteeseen","associationsJunctionJunction":"Risteys–risteys","associationsList":"Liitokset","associationsStructure":"Liitetty rakenteeseen","noAssociations":"Liitoksia ei löytynyt","associationFilterPlaceholder":"Suodata kohteen otsikon mukaan","associationsLimitNoticeTitle":"Kaikkia liittyviä kohteita ei voi luetella","associationsLimitNoticeMessage":"Vain {number} ensimmäistä liittyvää kohdetta luetellaan. Näytä lisää hakemalla kohdetta."}